[
  {
    "ApplicationLink": "https://careers.adidas-group.com/jobs/senior-project-manager-agilescrum-master-team-services-157031",
    "Company": "Adidas",
    "DatePosted": " February 24 2017",
    "Experience": "",
    "Hours": "",
    "JobID": "157031",
    "JobTitle": "Senior Project Manager Agile/Scrum Master Team Services",
    "LanguagesUsed": "",
    "Location": "Portland, OR",
    "Salary": ""
  },
  {
    "ApplicationLink": "https://careers.adidas-group.com/jobs/director-project-management-agilescrum-team-services-157026",
    "Company": "Adidas",
    "DatePosted": " February 24 2017",
    "Experience": "",
    "Hours": "",
    "JobID": "157026",
    "JobTitle": "Director Project Management Agile/Scrum Team Services",
    "LanguagesUsed": "",
    "Location": "Portland, OR",
    "Salary": ""
  },
  {
    "ApplicationLink": "https://careers.adidas-group.com/jobs/director-software-engineering-agile-157028",
    "Company": "Adidas",
    "DatePosted": " February 24 2017",
    "Experience": "",
    "Hours": "",
    "JobID": "157028",
    "JobTitle": "Director Software Engineering Agile",
    "LanguagesUsed": "",
    "Location": "Portland, OR",
    "Salary": ""
  },
  {
    "ApplicationLink": "https://careers.adidas-group.com/jobs/assistant-service-manager-mac-support-154935",
    "Company": "Adidas",
    "DatePosted": " February 24 2017",
    "Experience": "",
    "Hours": "",
    "JobID": "154935",
    "JobTitle": "Assistant Service Manager - Mac Support",
    "LanguagesUsed": "",
    "Location": "Portland, OR",
    "Salary": ""
  },
  {
    "ApplicationLink": "https://careers.adidas-group.com/jobs/senior-business-consultant-pos-154779",
    "Company": "Adidas",
    "DatePosted": " February 02 2017",
    "Experience": "",
    "Hours": "",
    "JobID": "154779",
    "JobTitle": "Senior Business Consultant - POS",
    "LanguagesUsed": "",
    "Location": "Portland, OR",
    "Salary": ""
  },
  {
    "ApplicationLink": "https://careers.adidas-group.com/jobs/business-consultant-fico-155943",
    "Company": "Adidas",
    "DatePosted": " January 19 2017",
    "Experience": "",
    "Hours": "",
    "JobID": "155943",
    "JobTitle": "SAP FICO Business Consultant",
    "LanguagesUsed": "",
    "Location": "Portland, OR",
    "Salary": ""
  },
  {
    "ApplicationLink": "https://careers.adidas-group.com/jobs/senior-business-consultant-fico-155884",
    "Company": "Adidas",
    "DatePosted": " January 18 2017",
    "Experience": "",
    "Hours": "",
    "JobID": "155884",
    "JobTitle": "Senior Business Consultant FICO",
    "LanguagesUsed": "",
    "Location": "Portland, OR",
    "Salary": ""
  },
  {
    "ApplicationLink": "https://careers.adidas-group.com/jobs/business-consultant-sd-nam-155690",
    "Company": "Adidas",
    "DatePosted": " January 17 2017",
    "Experience": "",
    "Hours": "",
    "JobID": "155690",
    "JobTitle": "Business Consultant SD NAM",
    "LanguagesUsed": "",
    "Location": "Portland, OR",
    "Salary": ""
  },
  {
    "ApplicationLink": "https://careers.adidas-group.com/jobs/it-senior-business-consultant-omnichannel-pos-mf-154969",
    "Company": "Adidas",
    "DatePosted": " January 04 2017",
    "Experience": "",
    "Hours": "",
    "JobID": "154969",
    "JobTitle": "IT  SENIOR BUSINESS CONSULTANT OMNICHANNEL POS",
    "LanguagesUsed": "",
    "Location": "Portland, OR",
    "Salary": ""
  },
  {
    "ApplicationLink": "https://careers.adidas-group.com/jobs/it-senior-business-consultant-omnichannel-pos-mf-155017",
    "Company": "Adidas",
    "DatePosted": " January 04 2017",
    "Experience": "",
    "Hours": "",
    "JobID": "155017",
    "JobTitle": "Sr. Business Consultant Omnichannel Integration",
    "LanguagesUsed": "",
    "Location": "Portland, OR",
    "Salary": ""
  },
  {
    "ApplicationLink": "https://careers.adidas-group.com/jobs/senior-project-manager-agile-153032",
    "Company": "Adidas",
    "DatePosted": " November 09 2016",
    "Experience": "",
    "Hours": "",
    "JobID": "153032",
    "JobTitle": "Senior Project Manager - Agile",
    "LanguagesUsed": "",
    "Location": "Portland, OR",
    "Salary": ""
  }
]